{
    "high-alert-timeout-seconds": 30,
    "break-timout-seconds": 300,
    "recovery-timeout-hours": 10,
    "sensors": 
    [
        {
            "name": "pir_sensor_1",
            "model": "pir",
            "connection-type": "rest",
            "rest-address": "192.168.1.10"
        },
        {
            "name": "pir_sensor_2",
            "model": "pir",
            "connection-type": "rest",
            "rest-address": "192.168.1.11"
        },
        {
            "name": "siren_1",
            "model": "siren",
            "connection-type": "pin",
            "pin-number": "1"
        },
        {
            "name": "strobe_1",
            "model": "strobe",
            "connection-type": "pin",
            "pin-number": "2"
        },
        {
            "name": "front_door_lock",
            "model": "lock",
            "connection-type": "rest",
            "rest-address": "192.168.1.12"
        }
    ]
}